{
    "ROI1_Name":"ROI1:PortName_RBV",
    "ROI1_MinX":"ROI1:MinX",
    "ROI1_MinY:":"ROI1:MinY",
    "ROI1_SizeX":"ROI1:SizeX",
    "ROI1_SizeY":"ROI1:SizeY",
    "Stats1_Total":"Stats1:Total_RBV",
    "Stats1_Min":"Stats1:MinValue_RBV",
    "Stats1_Max":"Stats1:MaxValue_RBV",
    "Stats1_Sigma":"Stats1:Sigma_RBV",
    "Stats1_Mean":"Stats1:MeanValue_RBV",

    "ROI2_Name":"ROI2:PortName_RBV",
    "ROI2_MinX":"ROI2:MinX",
    "ROI2_MinY:":"ROI2:MinY",
    "ROI2_SizeX":"ROI2:SizeX",
    "ROI2_SizeY":"ROI2:SizeY",
    "Stats2_Total":"Stats2:Total_RBV",

    "ROI3_Name":"ROI3:PortName_RBV",
    "ROI3_MinX":"ROI3:MinX",
    "ROI3_MinY:":"ROI3:MinY",
    "ROI3_SizeX":"ROI3:SizeX",
    "ROI3_SizeY":"ROI3:SizeY"
}